<PAMDataset>
  <PAMRasterBand band="1">
    <Description>coastal_blue</Description>
    <Histograms>
      <HistItem>
        <HistMin>113.5000806451613</HistMin>
        <HistMax>6313.499919354838</HistMax>
        <BucketCount>6200</BucketCount>
        <IncludeOutOfRange>0</IncludeOutOfRange>
        <Approximate>1</Approximate>
        <HistCounts>1|0|0|1|0|0|0|0|0|0|0|0|0|0|1|0|0|1|0|0|0|0|1|0|0|0|0|0|0|0|0|0|2|2|0|0|0|1|5|0|2|2|2|4|1|0|2|1|1|7|7|2|5|6|4|4|8|2|9|9|2|12|10|1|10|7|18|22|3|14|15|3|12|20|8|19|23|7|17|26|7|28|46|13|25|38|6|46|51|5|48|58|5|50|18|42|51|29|60|69|22|56|80|24|69|93|34|64|73|31|70|94|34|69|115|14|89|117|14|116|51|74|112|59|116|118|47|112|130|62|96|136|60|121|135|59|125|152|82|120|158|80|121|165|82|84|167|86|96|175|91|90|217|26|156|183|29|169|182|21|161|126|112|151|111|128|172|108|140|171|105|146|158|123|109|157|108|93|166|103|100|176|142|103|174|107|107|152|109|93|128|116|141|111|134|113|146|123|118|150|97|62|173|47|156|100|97|148|114|94|142|124|100|139|112|95|123|92|87|137|120|82|107|107|74|104|108|79|109|109|76|104|87|94|89|101|79|104|112|82|93|102|85|98|92|83|78|83|66|107|100|51|64|70|83|99|63|90|83|72|76|80|81|72|127|78|71|95|82|70|90|65|74|78|58|73|63|63|72|83|52|72|96|79|87|89|68|69|80|71|72|87|64|43|72|71|80|74|44|46|75|65|58|103|44|47|70|54|63|64|57|64|72|46|61|64|53|63|55|59|77|75|57|52|74|49|63|73|46|47|79|51|50|86|54|39|61|64|54|77|63|65|32|86|49|44|85|50|36|92|50|24|91|60|23|80|45|44|100|63|40|81|55|38|99|52|33|75|61|30|51|79|37|59|89|41|62|85|40|67|71|28|75|78|35|65|103|42|53|82|27|58|91|27|46|87|31|63|78|41|55|101|51|66|64|40|56|94|34|54|96|29|55|87|38|47|98|45|50|83|40|59|74|71|53|72|65|56|72|66|61|78|57|54|75|59|71|78|41|53|85|44|59|93|57|69|82|47|54|80|31|57|95|39|56|85|47|59|82|45|60|88|44|47|90|39|66|83|52|55|88|41|61|100|37|65|108|46|68|86|44|76|86|38|73|76|45|78|68|49|118|97|49|70|81|48|88|86|38|85|75|45|102|88|53|92|85|60|98|65|53|101|55|61|105|97|54|120|62|62|100|83|45|124|67|67|132|66|56|124|61|61|121|79|57|123|70|51|150|69|68|137|81|70|142|64|99|95|81|116|81|82|104|87|69|109|78|63|126|87|78|142|82|65|121|84|58|137|72|73|128|63|65|114|66|83|131|71|63|133|78|60|157|79|54|127|75|68|149|69|80|137|77|148|81|88|127|58|87|146|67|83|119|71|66|137|74|66|129|73|72|142|77|72|121|74|100|98|55|128|70|55|128|71|52|110|80|66|136|75|72|120|69|91|104|82|90|107|59|131|69|81|117|86|75|117|78|64|126|67|78|122|61|67|101|79|113|91|62|109|87|71|118|92|57|121|61|61|125|60|67|132|54|94|98|71|87|99|71|84|97|65|125|76|63|110|68|74|101|71|63|123|67|63|118|70|74|92|65|104|82|79|84|65|79|71|78|77|83|93|47|102|79|64|100|59|81|93|67|92|88|56|83|79|76|106|73|56|75|65|72|100|72|72|125|78|78|84|64|75|75|71|84|93|79|92|69|88|91|57|71|88|82|78|106|59|81|70|66|89|77|53|100|70|77|83|72|73|96|73|79|76|74|57|63|95|79|59|56|76|57|69|95|64|83|87|69|83|69|83|87|64|92|70|71|87|64|80|74|75|87|61|74|61|71|62|79|98|65|70|75|76|105|81|50|97|68|71|53|78|75|67|86|79|58|84|58|67|64|59|83|72|80|60|59|74|73|81|70|51|84|69|66|59|78|70|55|62|75|74|92|49|69|58|78|81|77|59|65|55|86|61|73|59|53|66|84|58|68|74|56|66|68|67|68|99|63|82|72|59|83|63|73|71|65|66|69|65|85|74|71|81|50|76|63|75|49|74|56|68|64|92|55|49|86|48|82|60|69|65|62|73|65|63|54|82|70|57|49|58|52|74|53|66|68|59|74|58|66|68|49|55|50|68|49|58|57|69|58|65|53|56|72|46|49|64|62|46|56|67|57|69|70|48|65|59|58|57|53|58|42|64|72|69|50|64|62|47|73|50|62|62|74|73|44|47|56|52|54|54|85|50|51|50|50|68|53|63|64|63|52|55|58|66|52|68|63|68|53|62|51|59|54|73|68|43|52|46|66|56|65|46|53|71|67|61|63|62|59|57|68|67|61|55|57|66|68|55|46|44|62|73|57|57|59|59|51|56|75|50|55|69|62|48|68|62|61|53|64|53|48|71|55|54|50|62|69|56|56|58|43|66|63|49|54|56|67|56|69|50|48|55|50|57|66|59|60|55|61|57|62|64|53|70|62|56|61|71|45|63|64|61|66|50|52|63|61|65|63|74|81|41|54|70|53|62|42|54|62|61|63|49|65|64|63|56|81|58|48|61|47|47|58|50|34|59|65|66|59|63|50|48|59|58|72|56|63|44|55|49|50|47|48|41|53|33|56|51|35|48|47|47|39|45|45|46|36|45|54|38|55|57|57|40|48|44|53|43|35|62|47|44|39|50|40|30|50|37|52|51|42|38|26|45|41|43|51|35|37|39|54|51|34|34|41|46|34|45|35|47|29|47|51|29|34|27|36|40|45|28|14|34|38|29|24|36|45|28|29|39|36|33|38|38|34|30|41|34|21|35|37|32|31|26|32|28|20|36|35|22|39|37|29|30|33|28|36|51|38|30|42|31|38|37|45|41|25|34|29|31|47|38|34|29|30|17|35|25|25|42|27|36|32|30|24|36|41|20|29|31|33|32|26|30|27|32|33|27|26|29|36|17|34|31|33|25|23|29|18|35|29|24|23|23|33|16|22|18|25|13|20|25|13|27|26|19|14|30|16|22|21|27|21|17|23|27|15|27|12|22|25|10|10|21|21|23|14|17|17|16|17|18|17|14|16|12|10|21|22|11|18|7|6|13|18|20|14|19|10|7|16|10|16|11|14|7|16|13|7|12|10|5|11|13|8|7|14|16|5|17|8|11|6|15|10|7|11|4|10|11|11|11|9|12|10|10|8|11|5|15|4|12|12|8|9|10|12|7|7|11|5|5|10|9|5|11|11|2|7|17|9|3|13|7|3|4|7|5|4|9|10|7|6|6|2|10|4|4|8|3|7|9|14|12|7|8|8|1|7|15|2|3|8|1|7|11|4|3|5|7|3|5|6|3|2|9|9|4|3|8|1|7|4|6|5|5|6|2|3|6|1|8|7|2|3|10|4|2|6|4|2|6|9|1|4|4|4|1|5|6|0|8|6|0|2|7|8|0|6|7|1|6|5|0|2|5|4|2|6|2|3|5|8|2|1|5|3|5|5|4|2|3|5|0|2|4|1|2|6|5|0|8|3|1|8|5|4|1|3|2|1|1|6|2|4|3|1|10|6|5|0|9|6|2|7|1|0|9|4|1|2|6|4|0|5|12|0|8|4|7|1|7|5|1|6|8|1|4|5|3|2|5|8|0|4|8|2|4|2|3|1|11|2|1|1|8|6|4|3|5|2|3|3|0|10|6|0|9|2|5|0|5|4|0|5|4|4|8|3|6|1|3|10|0|2|4|6|1|6|5|1|2|6|2|4|2|4|0|5|2|0|8|8|1|0|6|8|0|2|8|0|3|6|3|0|3|0|0|6|3|1|4|3|3|1|3|3|1|6|3|4|4|6|3|1|11|1|2|7|1|4|1|7|1|1|1|6|0|5|6|5|1|4|7|0|6|3|1|2|3|8|0|4|5|1|0|4|4|3|2|3|1|8|3|3|1|5|4|1|7|1|3|5|3|2|2|6|6|0|3|4|1|5|1|5|0|5|9|1|9|4|2|3|5|7|0|2|4|4|4|3|4|2|3|6|1|4|1|0|1|4|4|2|4|4|2|5|4|5|0|3|10|0|3|0|10|1|2|7|0|5|3|5|2|6|1|1|1|5|6|1|2|2|0|3|6|1|5|6|5|2|5|4|1|3|0|2|2|3|3|1|4|5|1|0|4|3|1|6|5|2|4|5|3|0|5|3|1|7|4|3|0|0|5|0|3|6|3|2|3|2|0|3|1|1|4|9|2|3|3|5|1|3|6|1|10|4|5|1|4|4|3|1|3|1|6|2|4|4|3|2|3|5|2|6|2|2|6|0|3|5|3|3|3|3|2|1|4|1|2|1|3|3|2|2|5|3|7|3|2|3|2|1|1|4|3|2|1|3|1|1|1|2|4|3|2|1|1|4|0|2|2|1|0|2|1|2|2|2|3|1|6|2|2|5|4|2|4|2|3|3|2|7|3|4|7|4|1|3|7|6|3|9|7|2|8|1|4|1|5|1|2|7|3|3|2|1|1|2|4|3|4|3|4|1|1|1|3|1|2|2|1|6|1|2|1|5|3|1|3|4|3|2|4|4|3|4|9|5|1|3|6|5|1|2|7|2|2|2|1|0|2|2|0|6|2|3|3|4|1|1|3|2|7|2|0|0|2|4|2|4|0|3|2|2|4|2|2|1|3|1|4|3|1|0|2|0|3|2|3|2|1|2|2|3|1|2|5|2|3|1|3|1|0|4|3|1|2|0|1|4|1|3|4|4|2|1|8|1|3|2|3|0|2|0|1|1|7|4|2|1|2|5|6|5|4|2|2|2|3|5|2|2|0|4|3|0|4|3|3|2|2|4|4|2|1|2|3|3|2|0|3|4|1|5|5|3|2|4|5|3|4|2|4|2|2|2|2|1|5|5|2|1|2|0|2|0|3|1|3|1|2|1|1|2|1|3|3|2|3|2|3|3|2|2|2|3|2|4|1|2|0|5|3|3|1|2|2|4|3|1|1|1|3|6|7|1|4|2|4|3|1|3|1|1|4|3|3|2|0|0|3|1|1|2|0|0|4|2|2|0|3|0|3|2|3|1|2|0|4|4|3|0|4|1|0|5|1|3|3|4|0|2|3|4|1|4|4|1|3|1|8|4|2|0|4|6|1|6|2|2|3|2|2|3|2|1|1|3|3|1|4|6|5|2|2|1|1|2|1|2|2|1|2|2|1|4|3|1|2|2|2|1|3|1|1|0|4|4|0|4|1|1|1|5|0|3|2|3|2|1|2|2|6|3|5|4|3|1|2|1|2|4|1|0|3|0|4|4|1|3|2|2|2|1|3|1|2|0|2|0|3|3|3|2|2|3|1|2|1|2|3|1|2|2|2|4|1|1|1|3|1|3|2|1|1|1|4|2|3|2|1|3|3|5|0|2|2|1|4|2|3|3|0|5|1|4|1|4|3|4|3|3|4|3|2|3|0|2|5|1|3|4|1|2|2|4|3|1|2|6|3|2|1|2|0|4|1|1|2|0|4|2|3|7|1|1|2|1|1|1|1|3|1|1|2|2|3|1|1|3|1|1|2|2|0|3|7|2|3|1|2|4|2|4|2|2|2|2|1|1|3|4|4|1|4|1|2|2|2|3|2|3|2|2|3|3|4|0|2|1|0|0|2|2|2|1|1|0|1|2|0|3|2|4|4|0|0|3|2|1|2|2|0|1|2|2|3|1|2|2|3|2|0|3|2|1|0|5|4|1|1|1|3|2|1|0|0|1|3|1|2|1|2|4|0|0|0|0|0|2|2|2|2|1|2|0|4|3|2|1|1|0|6|1|2|3|2|2|3|2|2|3|4|1|1|4|2|3|1|3|1|1|4|1|2|1|1|0|1|3|1|0|1|0|4|3|1|2|1|5|3|4|2|3|0|2|2|1|1|0|3|3|2|8|2|5|2|2|1|1|2|0|1|0|1|1|3|0|2|0|2|1|1|1|2|3|1|2|1|2|1|1|2|0|0|4|0|3|0|1|2|3|3|1|3|1|2|1|1|0|4|2|1|1|1|2|0|2|3|2|4|4|2|3|1|1|1|2|3|0|2|0|2|1|6|0|0|2|0|1|0|1|1|4|1|1|1|1|0|2|0|1|0|2|2|0|3|1|0|0|1|1|2|2|1|1|4|0|0|2|0|2|0|3|5|3|2|1|2|1|1|3|2|0|3|1|3|0|1|4|4|2|1|2|0|0|3|1|0|1|0|1|2|1|3|3|1|0|1|7|0|2|0|1|2|2|0|4|2|1|4|1|2|0|3|2|1|0|0|1|4|1|0|2|1|1|1|1|1|4|0|3|0|2|1|1|2|1|1|4|2|1|2|0|2|0|2|1|3|1|5|1|2|0|1|2|3|0|1|1|1|2|2|0|1|4|2|1|2|1|0|0|0|3|2|0|2|0|1|1|4|0|0|3|2|1|1|2|1|2|1|1|1|1|0|0|3|2|0|2|2|2|2|1|0|3|1|3|3|1|2|1|1|0|0|0|3|1|0|1|0|2|2|5|1|1|0|0|1|1|2|0|4|1|1|2|2|1|3|0|1|2|0|0|0|0|4|2|1|1|0|2|0|3|3|1|1|1|2|2|0|0|0|1|3|2|0|3|0|1|0|0|0|2|2|3|0|2|1|0|3|2|1|2|1|1|0|0|2|3|0|1|2|1|1|2|5|1|1|0|0|1|3|1|3|1|0|1|1|3|0|0|0|1|1|2|0|0|3|1|2|2|2|0|1|1|0|0|0|1|2|4|2|4|0|4|0|1|1|2|2|3|0|1|1|1|0|0|1|2|1|2|2|3|1|2|1|0|1|6|2|1|0|2|1|0|2|0|2|2|0|1|3|0|4|0|2|1|1|2|0|1|2|3|2|1|1|1|0|1|1|0|4|2|3|0|2|4|2|2|3|2|1|2|0|2|0|1|0|1|0|1|1|0|3|1|3|0|1|1|2|2|1|1|3|1|3|4|3|2|1|2|1|0|4|1|1|1|1|1|2|4|1|2|1|0|1|2|1|0|0|1|2|2|1|0|2|2|0|1|2|1|1|1|0|1|3|1|1|2|1|0|0|0|1|1|1|1|0|2|0|3|1|3|0|1|1|0|2|2|1|1|2|0|2|1|1|0|0|1|1|2|0|2|1|1|0|3|0|1|1|1|0|1|1|0|1|0|1|1|0|0|1|0|2|1|1|1|1|1|1|1|1|0|1|1|0|1|1|0|0|1|0|0|1|3|1|1|0|1|2|1|0|1|4|1|1|2|0|2|1|4|2|1|2|0|1|3|1|1|2|0|3|3|1|1|0|0|4|3|0|0|0|1|2|0|1|2|1|2|1|1|0|0|1|0|0|1|0|1|3|2|0|2|1|1|1|1|0|2|0|0|2|1|0|2|1|2|2|0|3|0|0|0|4|3|0|1|0|2|1|0|2|1|1|1|0|0|1|2|1|2|0|1|3|3|0|0|2|2|3|0|2|2|1|1|1|1|1|1|1|0|0|0|1|0|1|1|2|0|1|1|2|2|1|0|2|2|1|1|2|2|1|0|0|1|1|1|2|1|2|0|2|1|1|0|1|0|2|1|0|0|0|0|0|1|0|1|1|1|0|0|1|3|0|2|0|1|1|0|1|1|1|2|3|1|1|0|0|2|0|1|0|0|2|3|4|2|1|2|1|1|1|0|1|1|1|1|3|2|1|1|1|1|0|1|0|1|1|4|0|1|3|3|0|0|0|0|0|1|2|2|0|0|1|3|0|0|1|2|1|1|1|1|3|1|3|3|3|0|4|1|2|0|4|1|0|1|1|1|3|0|1|2|1|0|2|2|2|2|1|2|0|0|0|1|1|1|0|4|1|0|1|1|0|4|0|3|2|0|2|2|1|1|0|0|3|0|1|0|2|0|0|0|0|2|0|0|3|1|1|1|0|4|0|0|4|0|0|0|3|4|2|1|0|4|0|0|1|0|0|0|1|0|0|1|1|2|2|1|1|1|0|0|0|0|1|0|0|3|1|2|1|3|1|1|1|0|1|2|0|0|2|1|1|3|0|2|0|0|1|2|1|1|0|3|1|0|1|2|0|0|0|0|2|2|0|0|2|2|0|1|2|1|0|3|0|3|1|0|2|1|0|1|2|0|1|2|3|1|1|0|2|1|0|0|1|0|1|0|1|1|2|1|0|0|2|1|1|0|1|0|0|0|1|1|0|0|4|4|0|2|0|1|0|3|1|1|1|0|2|0|2|0|1|0|1|0|2|0|5|0|1|1|1|0|0|1|1|2|0|3|1|1|1|3|0|0|0|2|1|1|1|1|1|1|1|0|0|3|1|0|3|1|1|0|0|0|0|2|0|3|0|1|0|2|0|1|0|2|1|0|2|1|1|0|1|0|1|1|5|0|1|0|1|0|0|1|2|0|0|0|2|0|1|1|1|1|0|0|0|2|0|1|1|1|0|0|0|0|2|0|2|0|2|0|1|0|0|1|1|1|1|1|0|0|1|1|0|1|1|1|0|2|1|0|0|1|2|3|2|0|0|1|2|1|0|0|3|1|0|1|2|3|0|1|3|1|0|2|0|1|0|0|2|0|1|0|0|4|1|0|0|0|0|0|1|1|2|0|2|1|2|1|1|1|2|2|0|0|2|2|1|1|3|0|1|0|3|1|1|2|0|0|2|0|0|0|0|0|1|1|1|3|0|0|0|0|2|1|3|1|0|0|1|3|1|1|0|0|1|1|1|1|0|2|0|1|2|2|0|1|0|1|0|3|0|1|5|0|1|3|0|1|2|0|2|1|0|1|0|2|0|5|0|1|0|0|0|1|1|1|0|2|3|0|0|1|1|2|0|0|1|1|2|2|1|0|0|1|1|0|2|0|1|1|3|1|1|0|1|3|0|0|1|1|1|1|0|3|1|1|1|1|1|2|4|0|1|1|1|1|1|1|2|1|0|2|1|0|2|1|1|1|0|0|1|1|1|0|2|0|1|2|1|0|0|0|0|0|0|0|0|0|1|1|2|1|1|1|4|0|2|0|1|0|1|1|3|2|0|3|0|0|0|0|0|0|0|2|1|0|1|0|1|1|0|0|1|0|1|1|3|2|2|0|0|2|1|1|0|0|2|0|0|2|0|3|1|1|0|2|1|2|0|1|0|1|3|2|0|1|1|3|1|0|0|0|2|0|1|1|2|3|2|0|2|0|0|0|2|1|1|0|0|1|1|0|1|1|1|0|1|0|1|0|2|0|2|1|1|2|1|0|2|0|2|2|1|2|2|1|1|0|0|1|1|1|1|1|1|1|0|1|0|0|0|0|1|1|0|0|1|2|1|1|0|1|2|2|4|2|0|2|1|1|2|2|0|2|3|1|2|1|2|1|0|0|0|1|0|0|0|0|3|1|0|1|1|1|2|1|4|1|0|0|0|2|1|0|1|3|0|0|4|3|1|4|1|2|2|2|1|1|2|3|0|0|2|4|0|0|2|1|0|1|1|0|1|2|1|1|1|2|0|0|0|0|2|0|1|3|2|1|0|4|1|1|0|0|1|2|1|1|2|0|2|2|2|1|3|1|1|1|1|0|0|0|2|1|1|1|1|0|0|1|0|0|0|1|2|0|0|3|0|1|5|2|1|1|1|2|1|1|2|0|2|0|2|1|0|2|1|2|0|1|0|1|1|0|1|1|0|1|1|0|0|1|0|0|0|0|0|0|1|0|3|1|2|0|2|2|1|0|1|3|1|3|1|1|2|0|2|0|1|0|0|0|1|2|3|1|1|0|0|2|0|2|0|2|0|0|2|0|1|1|1|1|0|0|1|1|1|0|0|2|0|0|2|0|0|2|4|0|1|1|0|1|2|0|3|2|1|0|2|0|0|0|0|0|1|2|0|1|0|0|0|0|0|3|0|0|2|0|5|0|2|2|2|0|1|0|4|3|0|0|1|1|3|3|0|1|1|0|1|1|0|2|0|0|0|1|2|1|0|1|2|3|0|0|1|3|0|2|2|1|4|2|2|0|0|0|2|1|1|1|2|0|1|0|3|1|0|2|1|2|0|1|2|2|1|1|1|2|1|3|1|0|1|0|2|0|1|0|0|1|0|1|1|3|2|1|1|4|0|0|0|2|0|1|0|2|1|1|4|1|1|0|2|0|2|0|0|0|2|1|3|1|1|1|0|0|0|0|0|0|1|3|4|0|2|0|1|1|0|1|3|1|0|1|0|0|0|0|2|3|0|2|0|3|1|1|1|0|1|1|1|2|0|1|2|1|3|0|1|1|0|3|1|1|2|1|3|1|2|0|1|1|3|2|1|0|0|2|1|3|0|1|0|1|1|1|0|1|0|1|0|0|2|3|1|0|1|2|2|1|1|1|0|1|0|1|0|1|1|1|1|3|1|2|4|0|2|1|0|1|0|0|1|2|1|3|1|1|1|0|0|0|0|1|0|0|1|3|1|0|0|0|0|0|1|0|0|0|0|0|1|1|0|0|0|2|1|1|1|1|1|0|0|1|0|0|1|0|0|0|0|2|0|0|0|0|1|1|1|0|1|1|1|1|0|2|1|0|1|0|0|3|1|0|0|0|1|1|0|0|0|1|1|1|2|3|1|1|0|0|0|1|1|0|0|4|1|1|0|0|0|0|0|1|0|3|2|0|2|0|2|1|0|2|0|1|1|2|0|0|0|0|2|1|0|0|0|0|1|1|0|0|1|1|0|2|1|0|1|0|0|0|4|0|0|0|0|1|0|0|0|0|2|2|0|1|0|0|0|2|0|0|2|1|1|2|2|1|1|1|0|0|0|0|2|1|0|1|0|0|0|1|2|1|2|1|0|0|1|0|1|1|0|0|0|0|0|1|1|0|1|2|1|0|0|0|0|1|1|2|2|0|3|2|0|2|1|1|0|0|2|0|1|1|1|1|0|2|1|0|1|0|0|1|0|0|0|0|3|1|1|0|0|0|1|1|0|1|1|1|2|0|1|1|1|1|0|0|1|0|1|3|1|0|0|1|1|2|0|0|0|1|1|0|0|0|0|1|0|2|2|1|0|1|0|2|0|1|0|1|0|4|0|0|2|2|0|0|1|1|0|0|0|0|4|0|1|0|1|0|1|0|0|0|1|0|1|0|1|0|2|2|3|1|1|0|1|0|0|2|2|1|1|0|0|0|0|1|3|2|0|0|0|1|0|0|1|1|0|1|0|0|0|1|0|1|2|2|0|1|1|1|2|0|0|1|0|3|4|0|0|0|0|0|0|0|0|1|1|1|0|1|1|0|0|0|1|1|0|0|0|1|1|0|1|0|1|1|2|1|0|0|0|0|1|0|2|0|0|1|0|2|0|2|2|0|1|0|1|0|0|0|0|0|1|0|0|1|1|2|1|0|1|1|0|0|0|1|0|0|1|1|0|0|1|0|1|2|1|2|0|1|0|1|0|1|0|1|1|0|0|0|0|1|1|1|2|0|0|0|0|1|1|0|0|0|0|0|1|0|0|0|0|1|0|1|0|0|0|0|1|0|0|0|0|0|0|1|0|0|1|0|1|0|2|0|0|0|0|0|0|0|0|0|0|0|0|1|1|0|0|1|0|0|0|0|0|1|0|1|1|0|1|1|1|0|0|1|0|1|0|0|1|2|0|1|1|0|1|0|0|0|0|1|1|0|1|0|0|1|0|0|1|0|0|1|0|0|0|0|0|0|0|0|0|0|0|1|1|0|0|0|0|0|0|0|0|0|0|0|0|2|0|0|1|0|1|1|0|0|1|0|2|0|0|0|0|1|2|0|0|0|0|2|1|1|0|0|1|0|0|0|0|0|1|0|0|1|0|1|2|1|1|0|0|0|1|0|0|1|2|1|0|1|0|0|0|1|0|0|0|1|0|0|1|0|0|0|0|1|0|0|2|0|1|0|0|0|0|1|0|3|1|0|1|0|2|1|1|0|0|0|0|0|1|1|1|0|0|1|0|0|0|0|0|0|1|0|1|0|0|1|0|0|0|1|0|0|1|1|0|0|0|0|0|1|2|1|0|0|0|0|0|0|0|0|0|0|0|2|0|0|0|1|0|2|1|0|0|0|0|0|0|0|1|1|0|0|0|0|0|0|0|1|0|0|0|1|1|0|0|0|0|0|1|2|0|0|0|1|1|0|0|0|0|0|0|0|1|1|1|0|0|1|1|0|0|0|0|0|0|1|0|0|1|1|0|1|0|0|0|0|0|0|0|0|1|0|0|0|1|0|0|0|0|0|0|0|0|1|1|0|0|0|0|0|0|0|0|1|0|0|0|1|0|0|0|0|0|0|0|0|0|0|2|0|1|0|0|0|0|0|0|0|0|0|1|1|1|0|2|0|2|1|1|0|0|0|0|1|0|0|0|0|1|0|0|1|1|0|0|1|0|0|0|0|0|1|0|0|0|1|0|1|0|0|0|0|1|0|0|0|0|1|0|0|2|0|0|0|1|1|2|0|0|0|0|0|2|0|0|0|0|0|0|0|0|0|0|1|1|0|0|0|0|2|1|0|0|1|1|0|0|0|0|0|1|0|1|1|0|2|2|1|1|0|0|1|1|0|0|2|0|0|0|0|0|0|0|0|0|0|0|0|0|0|1|1|0|0|1|1|0|1|1|0|0|0|0|1|0|0|1|0|0|1|1|0|0|0|0|1|0|2|0|0|2|0|0|1|0|0|1|0|1|0|0|0|0|0|0|0|0|0|0|0|0|0|0|0|0|0|0|1|0|1|0|0|0|0|0|0|0|0|0|2|1|0|0|0|0|0|1|0|0|0|2|0|0|0|0|1|0|0|0|0|0|0|1|0|1|0|0|1|0|0|1|0|0|0|0|0|0|1|0|0|0|0|0|0|0|0|0|0|0|0|0|0|1|0|0|0|0|0|0|1|0|0|0|0|0|0|0|0|1|0|0|0|1|0|0|0|0|0|0|0|1|0|0|0|0|0|1|0|0|0|0|1|1|1|0|0|0|0|0|0|0|0|0|0|0|0|0|0|0|1|0|0|0|0|0|0|0|0|0|0|0|0|0|0|0|0|0|0|0|1|1|0|1|0|0|0|0|0|0|0|0|0|0|1|0|0|0|0|0|0|0|2|0|0|0|1|0|0|0|0|0|0|0|0|0|0|1|0|1|0|1|0|0|0|0|0|2|0|0|0|0|0|0|0|0|0|0|0|0|0|0|0|0|0|0|0|0|0|0|0|0|0|0|0|0|0|0|0|0|0|0|0|0|0|0|0|0|0|0|1|0|0|1|0|0|0|0|0|0|0|0|0|0|0|0|0|0|0|0|0|0|0|0|0|1|0|0|0|0|0|0|0|0|1|0|0|0|0|0|0|0|0|0|0|0|0|0|0|0|0|0|0|0|0|1|0|0|0|0|0|0|0|0|0|0|0|0|0|0|0|0|0|0|0|0|0|0|0|0|0|0|1|0|0|1|0|0|0|0|0|0|0|0|0|0|0|0|0|0|0|0|0|0|0|0|1|0|0|0|1|0|0|0|0|1|0|0|0|0|0|0|0|0|1|0|0|0|1|0|0|0|0|0|0|0|0|0|0|0|0|0|0|0|0|0|0|1|0|0|0|0|0|1|0|0|0|0|0|0|0|0|0|0|0|0|0|0|0|0|0|0|0|0|0|0|0|0|0|0|0|0|0|0|1|0|0|0|0|0|0|0|1|0|0|0|0|0|0|1|0|0|0|0|0|0|0|0|1|0|0|0|0|0|0|0|0|0|0|0|0|0|0|0|0|0|0|0|0|0|0|0|0|0|0|0|0|0|0|0|0|0|0|0|0|0|0|0|0|0|1|0|0|0|0|0|0|0|0|0|0|0|0|0|1|0|0|0|0|0|0|0|0|0|0|0|1|0|0|0|0|0|0|0|0|0|0|0|0|0|0|1|0|0|0|0|0|0|0|0|0|0|0|0|0|0|0|0|0|0|0|0|0|0|0|0|0|0|0|0|0|0|0|0|0|0|0|1</HistCounts>
      </HistItem>
    </Histograms>
    <Metadata>
      <MDI key="STATISTICS_APPROXIMATE">YES</MDI>
      <MDI key="STATISTICS_MINIMUM">114</MDI>
      <MDI key="STATISTICS_MAXIMUM">6313</MDI>
      <MDI key="STATISTICS_MEAN">890.65513153257</MDI>
      <MDI key="STATISTICS_STDDEV">700.4003099838</MDI>
      <MDI key="STATISTICS_VALID_PERCENT">6.011</MDI>
    </Metadata>
  </PAMRasterBand>
  <PAMRasterBand band="2">
    <Description>blue</Description>
    <Histograms>
      <HistItem>
        <HistMin>402.5000935278713</HistMin>
        <HistMax>5748.499906472129</HistMax>
        <BucketCount>5346</BucketCount>
        <IncludeOutOfRange>0</IncludeOutOfRange>
        <Approximate>1</Approximate>
        <HistCounts>1|0|0|0|0|0|0|0|0|0|0|1|2|0|0|1|0|1|1|1|0|3|3|4|2|2|4|1|6|7|6|0|5|7|1|13|6|15|3|9|14|20|4|14|19|5|29|31|28|10|26|34|42|18|32|42|9|57|50|68|19|61|78|72|27|57|90|16|107|81|113|34|81|111|27|118|94|150|41|130|119|139|54|77|143|47|179|101|128|65|143|125|153|80|122|188|63|179|122|146|96|116|174|163|96|110|193|64|204|146|170|77|121|187|83|200|136|214|79|197|125|155|99|135|189|73|180|132|167|68|171|123|153|102|121|156|61|149|115|160|75|150|95|126|111|84|156|87|165|96|136|104|79|157|82|178|80|161|77|141|69|117|107|77|137|76|160|62|125|65|131|80|111|77|63|144|76|151|64|121|61|70|136|56|137|63|128|68|99|59|94|73|51|131|59|115|65|102|62|112|63|69|98|47|131|52|124|47|91|60|96|63|61|81|51|87|45|90|44|99|43|61|80|39|96|50|79|43|86|44|105|32|59|79|45|86|44|91|33|74|32|47|70|50|77|37|82|48|75|34|45|86|44|84|53|73|42|102|35|69|47|30|77|38|91|31|69|41|66|40|66|46|40|73|39|90|43|82|35|81|45|69|30|39|83|39|82|46|83|28|76|40|77|30|58|84|43|65|50|78|34|70|38|75|43|46|75|36|66|45|72|39|75|27|55|38|46|77|32|67|28|79|41|64|31|59|53|36|54|59|51|22|68|42|72|17|48|50|34|41|34|54|32|53|37|66|17|50|39|32|53|51|49|36|57|37|64|23|51|34|23|42|42|31|36|35|37|50|19|50|47|28|39|48|38|23|29|31|50|19|38|34|64|25|53|44|31|30|31|47|30|45|33|51|19|51|39|25|49|41|71|30|43|51|63|27|63|31|44|46|57|45|59|48|53|65|28|62|47|39|52|65|55|42|53|40|86|56|46|61|72|51|61|47|49|43|66|58|51|32|81|35|47|50|44|72|50|47|39|48|57|61|42|37|50|65|66|28|36|53|40|39|46|52|39|50|77|64|38|46|63|60|36|55|46|47|57|43|41|41|60|42|43|35|55|57|64|36|53|40|73|28|43|56|41|73|40|42|39|48|69|57|37|40|60|68|40|53|52|36|93|52|67|28|81|58|64|31|58|69|81|36|62|79|76|33|70|65|31|77|96|65|36|52|78|62|39|88|77|96|38|88|63|43|98|87|77|42|91|100|92|36|79|74|110|39|92|96|67|89|95|90|68|96|81|100|66|131|99|72|44|104|135|82|59|103|88|113|59|93|75|69|106|101|99|90|77|123|96|61|138|94|76|52|114|130|89|67|110|82|79|114|124|90|92|106|122|94|95|103|112|85|111|118|112|96|51|101|115|87|72|102|102|88|105|103|89|99|90|84|87|87|120|91|97|81|125|112|66|97|94|95|115|88|117|89|103|92|99|82|112|103|100|93|97|99|138|78|101|119|106|92|99|104|80|100|114|117|78|100|123|107|72|114|113|100|94|119|128|100|109|111|122|104|87|92|88|74|113|109|101|87|110|121|88|98|107|113|76|96|94|111|104|89|109|95|93|86|96|117|66|92|74|114|102|98|94|94|54|112|99|72|96|77|103|89|88|108|96|86|97|92|84|101|80|89|107|92|88|88|98|102|92|84|102|93|82|82|84|88|64|101|93|55|87|94|68|90|99|91|83|78|72|96|92|75|73|98|73|82|75|116|105|88|66|99|84|66|92|105|104|49|104|119|94|90|80|105|89|83|86|93|79|81|96|86|99|82|90|84|106|71|89|89|80|90|94|89|71|88|100|92|64|108|94|67|91|96|104|75|86|88|70|67|76|99|76|79|79|73|93|78|78|90|81|84|66|82|79|76|57|71|90|63|82|74|99|78|69|87|91|61|78|86|71|84|73|90|62|69|94|96|63|77|99|79|77|79|68|97|68|61|66|68|75|66|85|78|84|69|58|78|77|72|78|58|91|63|89|67|51|85|67|60|66|67|100|66|89|73|62|83|59|74|69|74|77|69|66|61|79|77|76|67|60|63|88|71|67|71|56|62|50|91|61|57|58|63|56|75|70|52|61|45|59|73|53|40|63|54|66|61|76|56|72|52|55|92|43|70|60|76|51|49|67|64|46|43|64|65|68|45|71|61|54|43|66|71|65|51|44|55|71|60|66|63|61|61|55|47|71|66|58|45|59|70|54|67|60|59|56|52|55|54|54|57|58|59|56|53|50|65|77|46|58|63|64|46|57|63|51|51|42|57|61|58|66|53|49|60|61|55|72|66|79|48|61|51|69|43|66|53|64|49|47|58|81|60|51|60|80|67|49|58|66|65|63|49|54|72|64|39|60|78|77|48|53|66|54|57|34|71|57|72|46|57|69|65|54|56|57|85|73|52|71|62|70|42|53|81|72|62|54|72|73|68|33|77|81|71|26|71|80|69|57|49|72|68|67|40|73|75|43|59|55|76|55|68|41|73|76|71|37|70|70|75|72|44|75|71|48|41|71|65|49|69|40|73|55|41|35|53|58|42|34|62|51|40|36|43|64|66|28|43|51|65|56|31|49|41|59|23|32|39|33|45|16|54|51|53|20|38|56|39|43|6|40|54|53|10|45|52|54|40|6|55|49|46|7|54|64|40|51|6|43|47|46|10|37|48|34|58|6|43|33|53|10|43|47|41|49|2|38|45|43|6|37|44|42|48|13|37|46|34|3|45|39|39|37|19|33|31|31|11|40|25|30|38|18|39|44|34|18|26|30|46|28|7|39|49|38|19|14|38|31|35|5|35|38|26|25|19|33|32|28|10|37|31|16|24|20|29|31|39|6|28|38|29|19|17|24|27|31|10|22|25|34|21|17|44|25|26|16|21|35|26|18|15|37|32|27|15|27|23|29|24|18|31|15|30|21|27|10|29|21|13|21|18|33|23|12|25|21|22|12|22|28|28|14|10|24|33|14|10|21|25|22|19|18|21|22|25|15|20|12|22|15|18|15|18|23|11|16|17|17|7|5|17|25|17|15|7|19|20|10|8|10|20|21|12|9|16|10|8|6|9|13|13|11|8|16|8|8|10|15|5|14|10|12|12|13|9|8|10|13|14|10|6|4|8|5|6|4|12|12|9|4|14|11|9|1|14|9|11|5|4|12|6|6|6|13|2|8|6|7|9|7|9|5|10|4|6|6|11|6|8|7|10|8|11|6|10|5|6|7|9|5|4|12|11|9|5|9|7|8|5|9|5|7|0|6|8|5|3|4|5|6|6|1|9|6|5|7|15|8|3|8|6|9|3|2|8|10|5|3|7|9|7|4|7|10|4|2|5|7|3|5|5|5|6|7|5|5|5|3|5|8|4|2|3|3|5|3|8|4|6|3|10|6|6|4|2|6|3|4|6|5|2|5|4|4|5|4|6|3|3|7|3|3|3|4|3|8|5|6|4|4|4|3|8|5|3|5|7|5|11|7|6|3|12|7|5|2|3|5|3|7|6|2|4|1|4|8|5|2|4|1|5|4|3|4|5|5|4|1|9|2|2|4|6|7|4|0|7|8|5|5|0|2|6|3|5|7|8|3|5|3|2|5|4|6|5|6|1|8|7|3|5|5|6|1|3|8|4|2|2|7|5|2|0|3|4|5|6|0|3|4|1|4|8|4|4|3|9|6|4|2|5|7|5|1|0|5|4|4|3|4|4|1|12|3|1|3|4|1|4|4|0|1|4|2|3|4|4|3|5|5|7|3|2|5|2|4|2|6|1|5|4|6|4|5|4|2|2|7|4|2|1|7|1|2|5|2|3|3|1|3|1|7|3|5|3|1|5|0|4|6|2|3|5|1|4|7|4|2|8|4|2|5|3|2|1|2|4|7|3|5|3|1|1|5|4|4|7|1|2|0|3|6|1|6|1|5|4|6|3|3|3|6|4|2|1|4|1|0|3|7|2|1|3|4|5|4|5|2|2|3|3|6|11|0|5|4|2|2|2|1|2|5|3|3|2|5|3|0|5|4|5|2|1|3|5|5|3|1|6|4|2|1|6|2|3|4|5|0|3|2|3|2|2|6|6|6|4|1|5|2|5|4|1|1|4|6|2|4|3|5|0|4|4|3|3|1|2|2|2|1|1|4|4|4|2|2|5|1|1|2|4|4|0|2|4|4|4|3|4|2|5|1|4|4|7|3|3|6|5|4|3|4|3|3|1|6|3|5|1|3|3|1|2|2|3|1|3|4|2|2|0|3|1|4|3|8|3|2|1|4|0|2|6|6|3|5|2|5|3|4|2|2|4|2|1|4|3|1|2|3|0|2|3|2|0|3|0|3|1|3|2|3|6|3|4|3|4|1|2|3|1|1|4|2|3|3|2|5|3|5|3|2|6|5|6|2|0|4|1|1|1|1|4|5|2|2|3|4|4|1|1|4|7|1|2|4|0|5|5|1|2|0|2|4|4|1|2|1|2|2|5|0|1|1|5|3|4|4|3|2|4|0|4|3|1|2|3|3|6|2|2|5|0|3|1|1|5|3|1|1|1|2|1|1|0|2|9|2|1|3|4|4|1|3|3|5|0|3|1|3|5|1|5|0|3|1|2|5|2|3|1|1|0|5|1|0|2|2|0|3|3|1|1|6|7|4|2|2|5|2|3|2|0|3|2|0|1|2|6|3|0|2|1|2|3|2|3|1|4|4|0|5|4|1|2|2|4|1|2|1|2|4|2|1|2|3|4|1|3|1|0|1|3|2|3|1|4|0|4|4|4|6|1|2|0|4|1|4|5|0|3|3|2|1|3|1|5|2|5|0|2|6|1|1|3|1|5|2|3|4|4|2|1|2|5|2|1|3|0|6|3|3|1|1|1|5|3|2|3|2|2|4|1|3|1|5|2|1|2|3|4|0|1|1|4|5|2|2|3|0|2|0|2|3|0|3|0|2|4|2|0|3|3|1|5|1|1|1|2|3|4|4|5|7|1|1|2|2|2|2|2|4|2|2|1|0|0|0|0|3|0|2|0|3|4|5|0|2|0|0|3|2|3|0|3|1|1|1|0|1|2|2|1|2|1|4|2|4|2|3|0|2|2|2|4|1|4|1|1|2|3|6|3|7|0|3|2|2|3|3|2|2|6|3|7|5|1|1|2|5|1|1|4|5|2|2|3|1|3|0|0|4|2|0|1|7|0|6|1|3|0|3|2|1|3|1|3|3|2|2|1|2|1|3|1|4|6|0|0|3|1|0|1|2|4|2|0|3|0|2|0|2|0|5|2|1|3|0|2|1|2|4|1|2|1|2|0|2|2|2|4|2|1|2|1|3|3|1|3|0|2|1|0|4|1|2|1|3|1|1|1|2|1|2|2|5|2|2|0|2|1|1|2|2|2|1|2|1|2|2|2|5|2|3|3|1|1|3|2|0|3|1|4|0|3|1|1|3|0|3|1|2|4|1|2|1|2|0|2|1|5|0|2|0|1|2|0|3|7|2|3|0|3|1|5|1|1|2|3|1|1|2|2|1|1|1|2|1|1|1|1|1|2|2|3|1|2|2|3|0|0|2|2|0|5|0|1|1|3|2|0|4|0|3|1|4|2|2|0|3|2|0|1|2|1|3|1|4|2|3|2|1|0|0|0|4|1|1|2|1|4|6|2|1|2|2|0|0|3|1|1|3|1|2|4|1|4|3|0|2|2|3|1|0|4|1|2|2|1|2|2|4|1|2|2|0|2|2|2|1|1|1|3|3|2|1|0|2|0|0|3|1|3|2|0|0|1|4|0|2|1|1|0|1|2|3|3|3|0|1|2|1|1|0|0|1|2|1|2|0|0|1|3|2|2|0|4|3|0|0|1|0|1|2|1|2|3|1|1|1|1|2|0|2|1|2|2|2|0|4|3|2|1|5|1|4|0|1|1|2|1|1|1|0|1|1|0|2|1|2|0|2|2|1|0|2|1|3|2|3|2|2|2|2|2|1|1|3|3|1|1|1|4|2|0|2|0|0|0|0|1|4|1|1|2|3|1|3|1|1|0|2|2|1|1|1|0|0|0|0|1|1|2|1|1|0|0|1|2|2|4|3|0|1|2|2|3|0|0|1|1|0|1|1|1|2|0|3|1|1|3|0|4|1|4|1|0|3|0|2|3|3|1|3|2|1|3|0|2|1|2|0|3|2|0|2|0|1|2|1|1|2|1|1|0|1|0|0|2|1|1|1|2|3|1|1|0|0|1|3|0|4|4|0|4|2|2|0|1|1|0|2|1|1|3|1|1|2|3|0|3|3|2|2|0|3|3|4|1|0|4|0|2|1|4|1|1|2|3|1|1|2|3|3|2|0|1|0|3|0|2|1|1|1|2|1|1|1|1|2|0|2|0|1|1|1|1|2|2|4|1|1|3|1|0|2|0|0|1|1|4|1|2|1|1|1|3|1|2|2|1|1|1|1|3|3|1|1|2|1|2|1|2|1|3|2|1|1|3|1|0|0|1|3|1|2|0|2|0|2|0|1|1|1|0|1|3|2|1|2|0|0|2|1|1|2|0|0|0|2|2|1|1|0|0|2|2|2|2|3|1|0|2|0|1|1|1|2|4|3|0|0|1|0|3|0|3|3|1|2|2|3|3|2|0|2|0|1|1|1|2|1|2|3|1|1|1|1|3|3|0|1|2|1|2|1|0|2|2|0|1|1|1|1|0|2|1|1|1|4|1|0|2|1|0|1|1|2|1|1|1|4|1|2|0|1|1|0|1|0|4|1|0|1|3|0|3|2|2|3|1|3|1|0|2|1|2|3|1|0|2|1|1|2|1|3|0|2|0|2|1|2|2|0|2|2|0|0|1|2|3|1|1|1|1|0|1|1|4|2|0|0|0|2|2|0|2|1|3|1|1|2|0|1|2|0|1|3|0|1|1|2|1|0|0|2|2|1|0|1|3|2|1|3|2|1|2|0|1|1|1|2|2|2|1|1|5|1|1|1|3|2|1|2|3|1|4|3|1|0|1|1|1|1|0|1|1|1|0|2|1|1|2|0|1|2|0|1|1|1|0|0|1|1|2|2|4|2|3|0|2|2|1|2|1|1|3|0|2|1|0|1|1|2|1|2|2|2|2|1|0|2|0|4|3|1|1|1|2|1|0|1|0|3|1|1|0|1|3|0|1|0|1|0|3|4|1|0|1|6|4|2|2|1|0|0|2|1|0|1|1|1|0|2|1|2|1|3|0|4|2|1|3|2|1|1|0|3|2|1|1|3|2|1|3|0|1|1|2|2|0|1|3|0|1|2|1|0|0|1|1|0|3|1|0|1|4|1|1|0|0|4|1|1|0|0|2|2|1|0|2|0|1|1|1|1|0|1|1|0|0|4|0|0|2|0|2|1|0|1|0|1|1|1|1|3|1|2|2|0|0|0|0|3|0|0|0|2|1|0|3|4|0|2|3|1|1|3|3|2|2|0|0|1|2|0|2|0|2|0|0|1|2|2|2|0|1|2|2|2|0|2|2|0|1|1|0|0|0|0|1|0|0|0|0|0|0|1|0|1|0|1|2|0|1|0|1|0|1|0|2|1|1|0|0|4|0|0|3|3|1|1|0|2|1|0|3|1|2|1|0|2|0|0|2|2|1|0|0|1|0|1|0|0|0|0|1|1|1|2|0|0|2|0|2|0|1|1|0|0|1|0|1|0|0|2|0|1|3|0|1|2|3|2|0|2|0|2|1|1|2|0|2|2|0|0|4|0|2|2|2|2|0|2|1|0|1|2|0|1|3|0|2|1|1|2|1|2|1|5|0|0|0|2|1|3|0|0|1|4|3|0|0|1|2|0|2|0|1|3|1|1|0|2|1|0|2|0|0|0|3|1|0|0|1|0|3|2|0|1|2|1|4|0|1|1|3|1|3|0|1|0|2|1|1|0|1|1|1|0|1|4|1|3|1|1|3|1|1|1|0|3|0|1|0|0|1|0|0|1|0|0|1|2|0|2|0|0|1|2|0|0|1|0|0|3|1|1|1|1|0|1|0|0|0|1|0|0|2|2|1|5|1|0|3|1|1|0|1|0|1|2|0|1|0|1|0|1|0|0|1|2|0|1|0|2|1|1|1|1|2|1|3|0|0|2|4|3|2|2|0|3|0|2|2|1|4|1|1|2|1|1|2|3|1|1|0|0|3|0|3|1|0|3|1|0|0|1|0|1|1|1|0|0|1|1|0|1|1|2|1|0|2|0|0|1|1|2|0|0|1|3|1|3|0|1|1|0|0|2|0|0|1|1|1|2|2|0|2|0|1|1|3|1|1|0|2|1|0|0|0|2|3|1|3|0|0|0|1|1|1|1|0|1|1|2|1|1|1|1|0|0|0|2|2|1|0|2|1|0|2|0|1|0|2|0|0|3|0|1|0|0|0|2|1|0|0|1|1|0|0|2|0|1|3|1|0|0|1|0|1|2|0|1|1|2|1|1|3|2|0|1|3|2|2|1|0|1|1|3|1|3|3|1|2|1|1|0|0|1|1|1|1|1|1|1|0|1|0|1|0|3|0|1|2|1|1|1|0|2|3|1|0|1|5|0|1|1|2|3|0|1|1|1|0|1|1|2|0|3|3|0|1|2|0|1|0|0|1|2|1|0|0|2|0|0|2|0|0|2|1|2|2|2|1|1|1|0|3|1|1|2|3|0|0|2|0|0|1|0|0|1|1|2|2|1|3|1|1|2|0|0|2|1|0|2|0|2|1|2|0|0|2|3|1|3|0|1|1|2|1|2|0|4|1|1|1|3|2|2|3|3|0|0|2|0|1|1|2|1|0|2|1|1|2|1|1|0|1|1|2|1|1|1|1|3|1|2|3|0|1|0|0|0|1|1|0|1|1|3|0|1|0|2|1|0|1|1|0|0|0|1|1|1|5|2|0|3|1|1|0|2|0|2|2|0|1|1|0|1|1|1|2|1|1|0|1|0|0|2|1|1|2|0|0|0|1|0|0|2|2|0|0|1|2|2|1|2|1|0|0|1|1|3|1|1|0|1|1|1|0|3|0|0|1|0|0|2|2|2|0|1|1|2|1|1|1|0|2|1|0|0|0|0|1|1|2|1|2|0|0|0|0|1|3|0|3|0|2|2|1|1|0|0|1|2|0|1|1|1|1|2|0|0|1|1|2|0|0|4|0|0|1|0|0|1|1|1|1|1|0|0|1|2|0|2|0|0|1|0|1|1|0|1|0|0|0|1|1|1|0|2|1|0|1|1|1|1|0|1|1|0|1|1|2|1|1|1|1|0|1|1|0|0|0|0|0|1|0|3|0|0|0|1|0|2|0|3|2|1|1|0|1|1|0|2|0|0|0|1|0|2|1|1|1|0|1|0|2|2|0|2|2|1|1|1|0|2|1|0|1|2|1|0|0|2|2|0|2|3|0|3|0|0|3|0|0|0|3|0|0|0|0|1|1|0|1|1|2|2|1|1|1|0|1|1|3|1|1|0|1|0|3|0|1|2|1|1|0|0|1|0|0|2|0|0|2|3|3|1|0|1|1|0|5|3|1|1|0|0|1|1|2|2|0|2|0|1|1|2|1|0|1|1|0|0|0|2|0|1|0|2|1|1|1|1|1|0|2|0|0|1|1|1|2|1|2|1|1|0|1|0|3|2|1|0|1|1|0|1|0|0|3|3|2|1|1|1|0|0|0|4|1|5|0|0|1|4|1|1|1|1|0|0|0|1|2|0|1|5|0|3|0|1|2|1|0|1|0|0|2|0|1|0|1|1|1|2|1|1|1|2|1|1|0|0|0|0|0|1|0|0|1|0|0|1|0|0|0|0|1|1|0|1|1|1|0|0|0|0|0|3|0|2|0|2|1|0|0|1|0|2|0|1|2|0|1|1|4|0|1|0|0|3|2|1|0|0|0|1|1|1|0|1|0|0|2|0|0|1|1|0|4|0|1|1|0|1|0|1|0|3|0|0|3|3|1|0|1|0|0|0|0|0|3|1|1|0|0|1|1|0|0|0|0|0|1|1|2|0|1|1|1|0|0|1|0|1|0|3|0|1|1|3|2|1|0|0|2|0|2|2|1|0|0|1|1|2|0|1|1|1|2|0|2|0|0|1|1|0|2|1|2|0|1|2|0|0|1|1|0|0|2|1|1|0|1|2|0|0|0|1|2|2|3|0|0|2|2|1|1|2|1|0|2|2|0|0|0|0|1|1|0|1|1|1|1|1|1|3|0|0|1|1|0|1|3|1|0|0|0|1|1|1|1|1|0|1|5|0|0|1|0|3|2|2|0|3|1|0|0|2|1|0|0|2|1|0|2|0|1|1|2|2|1|0|0|0|0|0|0|1|1|2|2|1|1|0|1|1|1|1|1|1|0|0|1|1|0|0|2|0|0|0|0|0|1|0|0|1|0|1|1|0|1|0|2|0|0|0|0|1|1|1|2|0|0|2|2|0|0|0|3|0|1|1|2|0|1|0|1|0|1|2|0|1|1|0|0|1|1|1|0|2|1|1|1|2|0|0|0|0|0|0|1|1|0|3|1|1|0|0|1|2|0|1|1|1|0|1|0|1|1|0|0|3|0|1|0|0|0|0|2|1|0|1|2|0|1|1|0|0|2|0|1|1|0|0|1|3|0|2|0|1|0|0|0|0|0|2|1|0|1|1|0|1|0|1|0|0|0|1|0|0|1|1|0|0|2|1|0|0|1|1|1|3|1|2|0|0|1|0|0|0|0|0|0|0|0|2|1|0|0|1|1|0|1|1|1|0|1|0|0|1|0|0|2|1|0|1|0|0|2|0|0|0|0|0|0|0|0|2|0|0|1|0|0|1|0|1|0|0|0|1|0|0|0|0|0|0|0|0|0|0|0|0|1|0|0|1|0|1|0|0|0|0|0|1|2|0|1|0|1|1|1|1|0|0|0|0|1|0|0|2|1|0|2|0|0|0|0|0|0|1|0|0|0|0|0|0|1|0|0|0|0|0|0|1|0|2|1|0|0|1|0|3|0|0|0|1|0|0|1|0|0|0|0|0|0|0|2|0|0|1|0|0|0|0|0|0|1|1|1|0|0|0|1|0|0|0|1|1|1|0|1|0|0|0|1|0|0|1|0|0|1|0|1|0|0|0|0|1|0|2|2|0|0|1|0|0|0|0|0|0|0|2|0|0|1|0|1|0|0|1|1|0|2|1|2|2|1|0|0|0|0|0|0|0|0|1|0|0|1|0|1|1|0|0|0|0|0|1|2|0|0|2|0|1|1|0|0|1|0|0|0|0|1|0|1|1|0|1|2|1|0|0|2|1|1|0|2|0|0|3|0|0|0|0|0|1|0|0|1|0|1|0|0|0|0|0|0|0|1|0|1|2|0|1|0|2|1|0|0|1|1|1|0|1|1|1|1|0|1|0|0|2|0|0|0|0|2|0|0|0|2|0|1|1|0|1|0|0|0|0|1|1|1|1|2|1|0|1|4|1|0|1|0|2|0|0|3|1|0|2|0|0|0|0|2|1|3|0|2|1|1|1|0|1|1|0|1|2|1|1|1|0|0|2|0|1|0|1|0|1|2|1|0|0|0|0|1|1|0|1|0|1|1|2|2|0|0|0|2|0|0|0|2|0|0|0|0|1|2|0|0|1|2|0|3|0|1|1|1|0|3|1|1|0|2|0|0|1|0|1|1|1|2|1|1|1|0|0|2|0|2|5|0|1|1|0|0|0|2|0|0|0|0|1|0|0|1|0|1|3|2|0|1|1|2|1|0|0|0|1|1|0|0|1|1|1|1|1|0|0|1|1|0|0|2|0|0|0|2|0|0|1|0|0|0|0|2|0|0|1|1|2|0|0|0|0|1|1|2|2|1|1|0|1|0|1|1|1|1|1|0|0|0|1|1|2|0|0|1|0|0|1|0|0|0|0|0|0|0|0|1|1|0|0|1|0|0|0|0|0|0|1|0|0|0|0|0|0|0|0|0|0|0|0|0|0|0|0|0|0|0|0|0|0|0|0|0|0|0|0|0|0|0|0|0|0|0|0|0|0|0|0|0|0|1</HistCounts>
      </HistItem>
    </Histograms>
    <Metadata>
      <MDI key="STATISTICS_APPROXIMATE">YES</MDI>
      <MDI key="STATISTICS_MINIMUM">403</MDI>
      <MDI key="STATISTICS_MAXIMUM">5748</MDI>
      <MDI key="STATISTICS_MEAN">1162.9761180001</MDI>
      <MDI key="STATISTICS_STDDEV">671.3784909211</MDI>
      <MDI key="STATISTICS_VALID_PERCENT">6.011</MDI>
    </Metadata>
  </PAMRasterBand>
  <PAMRasterBand band="3">
    <Description>green_i</Description>
    <Histograms>
      <HistItem>
        <HistMin>563.5000905633037</HistMin>
        <HistMax>6084.499909436696</HistMax>
        <BucketCount>5521</BucketCount>
        <IncludeOutOfRange>0</IncludeOutOfRange>
        <Approximate>1</Approximate>
        <HistCounts>1|0|0|0|0|0|0|0|0|0|0|0|0|0|1|0|2|2|0|0|4|1|3|1|1|1|2|1|3|0|4|2|7|3|4|2|9|8|6|3|6|8|7|5|9|15|19|6|22|33|27|9|30|34|33|10|37|42|36|47|9|43|49|66|15|54|55|81|17|83|73|103|12|105|61|96|14|85|83|95|27|111|71|122|29|126|71|128|40|123|82|121|40|123|98|122|37|130|81|129|51|118|102|146|49|133|104|140|68|146|90|132|74|129|113|161|61|139|100|142|77|160|106|153|79|136|195|104|74|149|154|111|85|145|167|82|87|138|136|115|87|145|186|103|79|117|154|102|177|64|140|77|144|87|131|90|151|100|131|79|144|86|102|72|155|98|111|75|137|83|112|56|127|101|106|118|70|99|120|128|79|93|96|123|66|95|100|107|61|81|97|122|60|70|108|115|46|73|97|126|51|105|80|78|54|99|67|79|64|113|73|71|49|83|66|72|54|92|62|87|37|88|89|74|81|38|75|73|95|52|64|53|89|41|58|57|70|37|52|52|80|49|50|53|67|29|56|65|54|34|47|48|52|46|81|37|44|38|66|48|38|46|64|42|42|48|33|50|33|57|34|50|42|59|30|54|33|61|28|56|56|43|36|54|53|34|33|58|47|38|29|69|50|36|45|55|50|46|39|50|49|43|59|31|52|40|70|40|48|28|63|31|28|47|52|35|49|56|34|35|55|67|34|38|47|52|30|36|63|47|38|28|64|53|27|34|50|69|38|64|47|53|41|51|41|46|29|59|33|57|73|26|37|57|70|39|32|67|50|31|48|44|55|28|35|56|56|32|40|39|37|27|64|34|43|33|55|36|39|35|50|32|48|52|39|38|51|50|35|38|62|55|28|32|58|44|38|33|64|36|39|54|29|40|32|44|35|34|46|30|24|38|54|32|24|44|44|37|27|43|23|40|32|50|31|35|35|45|37|30|65|25|46|33|53|25|39|54|34|33|48|35|43|21|48|33|36|31|43|44|21|28|53|36|20|16|40|48|27|54|31|30|44|29|24|46|24|25|25|37|40|28|24|39|35|22|22|40|33|25|20|35|33|25|20|39|31|36|20|22|34|26|18|23|22|25|24|24|31|22|17|18|34|31|28|19|30|25|28|14|26|19|24|18|41|36|33|21|23|38|40|32|30|42|32|28|29|37|26|39|28|37|39|42|31|39|40|29|33|42|39|35|36|38|39|30|32|30|51|25|31|48|42|57|27|46|42|46|33|47|43|46|35|38|50|43|44|40|49|58|32|53|48|60|47|21|45|62|42|34|42|41|51|29|51|55|41|31|45|43|52|28|48|41|45|49|33|41|53|34|34|28|47|47|42|54|32|54|28|40|54|51|26|38|57|40|35|36|50|76|52|55|40|65|46|56|58|52|77|49|64|56|61|67|62|55|65|49|63|56|86|48|84|73|80|82|50|97|55|84|78|70|76|91|72|93|66|88|74|99|62|105|105|76|100|69|117|87|66|77|96|80|98|65|119|118|66|71|115|113|89|87|76|115|95|78|83|121|85|98|63|104|91|92|95|85|102|98|83|66|137|101|86|94|125|135|94|81|119|114|84|96|87|129|105|82|97|148|99|104|82|119|134|74|56|127|118|106|67|96|116|82|64|79|107|97|85|54|115|111|84|60|122|121|103|71|81|117|98|55|78|120|127|94|60|106|102|116|57|89|109|90|80|105|108|88|67|67|114|92|77|49|121|112|100|52|99|111|100|41|84|122|107|72|61|106|129|91|62|96|120|132|45|104|120|115|82|72|115|114|85|60|85|117|99|71|60|112|110|79|78|108|122|97|62|98|114|111|95|78|125|103|115|40|123|123|116|48|86|112|106|77|63|116|105|79|49|96|104|79|69|94|101|101|81|62|93|106|93|41|104|103|75|47|102|108|86|66|86|121|104|73|53|111|129|99|43|95|102|122|72|73|106|116|100|46|116|124|135|74|79|98|136|104|64|83|123|124|61|136|93|125|62|115|109|103|104|74|133|83|75|50|151|112|84|88|111|136|117|54|76|132|126|96|15|109|124|128|70|60|109|126|88|53|82|114|112|51|72|90|121|74|79|62|109|88|62|115|74|102|62|88|101|71|84|73|110|110|58|58|124|96|103|35|83|101|126|58|56|108|105|113|1|90|110|101|76|18|116|107|97|52|54|109|99|75|78|53|94|96|69|75|83|109|63|93|66|91|79|74|92|54|78|54|88|104|50|47|99|99|94|55|38|109|81|78|24|99|94|77|49|46|89|94|97|17|83|93|94|53|66|75|75|98|35|68|80|90|54|72|80|95|70|71|55|69|77|50|100|61|83|35|105|96|64|101|51|101|99|60|52|74|94|91|60|52|82|96|67|26|73|79|92|47|58|66|66|85|30|72|70|59|62|41|51|68|80|58|70|58|73|57|66|58|77|64|47|58|52|72|45|92|55|46|62|62|98|62|73|53|59|93|44|54|65|84|68|34|46|80|57|79|28|65|90|83|69|35|75|75|68|45|53|72|74|56|50|56|61|85|63|70|53|68|86|59|69|57|71|66|73|64|70|70|63|74|45|80|65|74|68|62|78|75|74|69|43|65|70|67|66|57|61|62|76|54|49|68|64|69|46|67|66|61|66|60|63|73|69|66|40|66|80|44|64|62|65|63|51|51|46|66|71|64|68|67|71|56|59|37|63|67|70|79|47|57|65|84|53|46|65|69|57|55|39|67|66|68|49|30|54|66|57|45|35|64|52|59|44|36|70|55|50|27|40|61|50|50|32|41|57|55|38|31|46|51|54|37|29|50|35|44|36|37|36|39|51|48|41|28|38|39|48|32|39|28|49|24|27|32|35|34|26|19|28|35|33|32|33|25|39|32|28|29|36|32|27|26|36|30|31|30|33|33|44|21|32|42|31|18|29|31|34|34|18|35|34|32|22|32|36|22|35|35|26|23|22|28|21|30|22|26|23|21|28|27|14|24|27|31|21|23|31|31|20|16|34|22|31|20|29|23|29|24|13|24|28|24|28|24|24|22|33|36|28|23|31|24|27|28|18|18|29|35|27|29|15|35|23|17|35|20|16|28|21|27|16|38|24|20|18|32|17|29|9|22|22|16|24|22|20|27|22|18|12|29|17|27|15|19|20|19|18|19|24|18|17|23|19|17|13|21|17|18|15|23|13|14|18|17|16|16|12|14|12|20|17|15|11|8|17|13|15|13|11|6|26|12|15|8|17|13|14|10|10|13|17|17|24|13|12|18|13|12|12|22|19|11|14|12|15|10|19|14|15|13|17|11|9|19|6|9|15|7|10|15|9|5|10|9|8|9|18|7|9|15|8|10|9|6|4|5|12|7|8|11|11|13|6|8|8|6|8|6|10|7|6|3|3|9|5|5|7|8|10|6|2|5|9|4|4|5|7|7|6|4|2|5|10|8|9|4|4|7|3|4|8|4|5|8|7|3|6|3|6|4|10|6|2|10|7|1|7|2|6|1|11|8|1|7|8|5|4|5|6|6|2|2|4|5|5|5|5|1|1|3|2|2|5|3|6|5|4|9|3|5|4|7|8|4|5|3|6|5|2|0|8|5|4|1|3|2|4|4|3|8|6|12|4|2|5|5|3|4|3|7|6|2|1|5|4|4|2|4|1|10|5|7|2|5|3|2|1|3|1|4|2|2|3|1|4|5|4|5|2|3|3|4|3|9|2|2|4|1|2|4|2|2|5|4|5|1|3|4|3|0|5|2|2|1|6|3|3|4|1|5|2|3|10|6|5|1|3|5|2|6|2|7|2|5|6|4|2|3|3|6|1|3|5|2|6|1|2|4|4|3|10|6|2|2|2|5|3|5|4|5|5|2|0|2|6|2|4|5|2|2|2|4|5|2|4|5|5|2|3|4|6|4|2|9|1|4|5|7|4|4|4|0|1|6|4|2|1|4|2|3|5|1|3|1|1|3|5|4|3|3|6|2|2|2|3|1|6|0|1|3|2|4|1|1|1|1|4|2|1|5|7|2|4|4|3|3|0|2|2|3|0|2|3|1|2|2|2|1|1|1|3|4|3|4|4|0|3|2|1|1|2|6|3|3|2|4|3|7|6|0|3|4|3|3|3|4|1|3|6|0|3|3|4|4|3|4|3|1|2|6|5|2|1|3|0|7|1|5|1|3|3|3|6|1|2|3|2|2|7|2|4|3|2|2|2|0|1|1|2|3|3|5|3|3|3|3|1|1|2|2|0|4|2|2|3|4|2|2|1|2|4|3|4|5|3|0|2|4|4|1|0|1|2|4|4|3|1|3|1|4|6|2|2|9|5|2|3|0|1|2|0|3|5|1|0|3|1|2|2|2|3|4|1|2|2|5|1|5|3|2|3|1|1|6|3|1|7|2|3|4|1|3|1|0|4|3|3|4|4|6|2|1|1|3|1|0|1|6|2|1|1|4|2|2|4|1|2|2|0|3|2|3|6|2|3|4|4|1|5|3|1|5|3|3|3|2|2|3|1|2|3|1|3|4|3|6|9|3|3|3|1|3|1|1|3|2|4|2|3|2|3|6|4|3|1|4|2|2|3|0|5|3|3|2|5|0|2|1|1|3|2|3|3|4|3|3|1|2|2|3|3|4|2|3|0|1|3|2|2|5|5|5|1|2|3|1|4|2|5|3|3|0|1|2|3|4|3|2|5|3|5|2|5|5|1|0|2|1|2|1|1|5|3|2|1|2|4|2|3|4|2|2|2|5|2|2|3|1|2|3|4|0|3|2|5|4|3|1|0|3|1|1|7|3|5|4|5|3|3|3|1|7|2|1|3|4|3|2|0|4|2|2|2|1|2|1|3|1|3|2|0|2|4|3|4|1|2|2|4|4|2|2|1|3|2|2|2|1|2|0|2|5|2|0|3|1|4|0|1|2|0|2|1|1|0|2|0|3|1|1|4|1|2|3|2|4|0|4|2|3|1|2|3|4|2|3|1|4|3|3|0|1|4|2|4|5|1|3|3|2|2|1|0|3|2|6|0|0|0|3|1|0|3|0|3|1|0|1|1|0|3|3|2|0|2|3|1|5|3|4|2|3|1|2|5|1|1|2|1|2|0|0|0|2|3|2|1|0|3|2|0|1|2|1|7|0|1|3|0|4|0|3|3|2|1|3|2|1|2|2|0|3|3|2|1|1|2|0|1|2|6|4|1|0|2|3|0|1|2|0|5|1|0|2|1|1|1|0|2|1|4|4|0|7|1|3|3|0|3|3|1|3|1|3|0|4|1|1|4|0|2|1|1|1|1|3|1|2|0|1|4|1|0|1|3|4|0|3|2|6|3|1|1|1|1|1|1|1|3|1|3|3|2|3|0|3|3|2|1|0|1|1|3|1|2|3|3|2|5|2|4|1|0|3|0|2|0|4|3|2|2|1|1|1|0|0|1|4|1|2|3|1|1|1|3|1|3|1|4|1|1|1|3|2|2|4|2|1|1|3|5|1|2|2|3|1|1|3|0|2|0|1|2|0|2|1|2|2|1|1|0|2|3|1|1|2|1|0|2|2|1|4|0|1|1|1|3|4|1|1|0|4|0|1|0|0|2|1|1|3|4|3|1|2|0|2|3|1|1|2|1|1|1|1|6|1|2|5|2|2|1|1|1|1|1|1|0|0|1|0|0|0|4|3|0|2|3|0|1|0|2|1|4|1|4|0|0|0|1|3|2|4|1|2|4|1|3|2|0|1|1|3|2|1|2|2|1|2|3|2|1|6|4|3|0|2|3|4|3|0|2|1|1|1|3|2|1|1|1|2|0|0|0|2|2|2|1|2|1|0|0|0|0|0|2|4|0|1|1|0|1|1|0|1|2|2|1|5|0|2|1|0|0|5|1|6|3|0|2|2|0|1|1|2|0|1|2|2|2|2|3|1|1|1|0|1|4|0|2|1|0|2|3|1|3|2|1|2|3|0|3|0|0|2|2|0|1|0|2|3|2|0|2|1|1|1|2|3|0|2|1|1|4|1|3|1|0|3|1|1|0|0|2|3|2|1|0|2|0|1|2|0|2|0|2|1|1|2|0|0|3|3|4|3|2|1|0|1|2|0|2|2|3|1|0|5|0|0|0|1|2|2|0|0|2|3|2|1|0|5|2|3|1|0|1|1|1|1|0|0|1|3|1|2|1|2|0|1|1|0|0|2|0|3|0|1|0|0|0|2|2|0|0|2|4|1|1|0|2|3|0|2|1|1|2|0|0|1|0|0|0|5|2|0|1|3|0|2|3|3|1|1|1|0|2|5|3|0|3|1|0|2|0|0|2|1|2|0|4|2|1|2|3|3|1|1|2|3|6|1|1|1|3|0|2|2|0|1|3|3|3|4|0|3|1|3|2|1|1|2|0|1|0|1|0|0|1|0|2|1|2|0|0|0|1|0|2|4|0|3|0|3|0|1|1|3|3|3|2|2|2|4|1|2|2|0|1|1|2|0|0|0|1|3|1|0|0|2|0|2|2|3|3|2|3|0|2|0|1|1|0|1|0|2|2|2|5|1|2|0|2|2|0|2|0|0|1|3|0|1|0|6|0|2|2|2|0|1|0|1|5|2|1|0|2|0|1|2|0|1|1|0|5|0|0|0|0|1|2|1|3|2|1|2|1|2|3|3|1|0|2|3|1|2|1|0|1|0|3|1|1|0|0|2|2|0|0|2|3|2|3|0|0|2|1|1|4|0|0|3|1|0|0|1|0|2|0|1|2|3|2|1|0|2|1|2|1|2|2|0|2|2|4|0|2|1|2|1|1|1|1|2|3|0|1|0|0|0|1|3|1|0|1|0|0|0|3|1|0|1|3|1|1|4|1|1|0|2|2|0|1|2|0|3|1|1|0|1|0|0|1|1|0|3|0|0|2|1|1|5|3|2|2|1|4|0|5|0|1|2|1|1|1|1|2|3|2|5|0|2|2|2|1|3|2|0|0|2|1|4|0|1|2|1|3|0|3|0|2|3|3|3|0|3|0|4|0|2|4|0|0|4|0|1|4|1|1|0|1|0|2|0|1|1|1|0|2|1|0|1|3|1|3|2|1|1|1|2|3|0|2|1|3|1|0|3|3|4|1|2|1|4|3|1|2|3|0|0|1|0|2|1|2|2|2|3|0|1|2|1|3|3|0|1|2|2|1|0|1|2|1|1|1|0|1|2|3|2|1|3|1|0|2|1|0|1|0|2|0|0|2|0|3|2|3|0|2|1|1|2|1|1|2|3|3|0|0|2|0|3|3|1|1|3|1|4|3|0|1|2|0|3|3|2|1|0|1|1|0|2|1|1|1|3|0|0|0|1|1|0|1|2|0|3|3|0|1|3|1|3|1|2|0|0|3|1|0|0|2|2|2|0|4|2|3|0|2|0|1|3|1|0|3|2|0|0|0|3|0|1|1|1|1|2|0|0|0|0|0|0|1|2|1|4|1|0|5|2|1|3|0|2|2|2|1|1|0|2|0|1|2|3|0|0|2|4|2|1|1|0|1|3|4|0|1|0|1|1|0|0|1|2|2|1|1|0|1|2|2|2|1|3|0|2|2|2|5|3|1|1|2|1|0|1|1|3|0|0|1|0|1|0|4|0|1|0|1|2|3|0|1|2|3|1|0|1|2|2|1|0|1|2|1|3|1|1|0|0|1|0|0|0|2|0|3|1|0|3|1|1|1|1|1|0|2|1|1|2|1|1|2|4|0|0|2|0|2|0|1|2|2|0|1|0|3|1|3|0|0|1|2|0|1|1|2|0|0|0|0|1|2|2|1|0|1|0|0|3|2|0|0|4|1|1|1|0|0|1|0|0|1|1|2|0|0|2|1|0|0|0|2|0|0|1|1|1|3|2|0|0|2|1|0|2|2|0|1|2|0|1|0|2|2|0|1|2|3|1|3|2|1|0|2|1|5|1|0|0|1|2|2|0|1|0|2|1|2|1|0|3|2|0|0|1|0|0|0|2|5|2|0|1|2|1|2|0|1|1|0|0|2|0|2|0|2|3|1|3|0|1|1|4|2|1|2|2|0|2|0|1|1|1|3|1|1|0|1|0|2|1|3|1|2|1|1|3|0|1|1|1|2|2|2|1|0|2|0|3|0|1|0|1|0|2|0|1|1|3|3|0|1|1|0|1|3|0|1|0|0|1|1|2|1|1|2|2|1|1|0|1|1|1|1|1|2|0|1|2|1|0|0|1|1|1|0|0|2|1|4|0|0|4|0|0|0|3|3|1|0|1|1|1|0|1|1|1|3|2|0|1|0|1|0|0|0|1|2|1|3|0|5|1|1|0|0|1|0|2|1|0|2|1|2|0|0|0|4|2|1|3|1|0|1|0|0|0|1|1|3|2|0|0|0|0|0|0|1|2|1|0|0|2|0|1|4|0|1|1|2|0|0|2|1|0|0|3|2|1|0|1|0|1|1|0|1|2|3|1|0|1|1|0|1|2|1|0|1|0|1|3|1|1|0|2|1|2|0|0|0|1|0|0|0|1|0|0|0|1|0|1|1|4|1|1|0|0|1|0|0|2|5|1|1|3|2|3|0|0|1|0|1|1|1|0|0|1|2|1|0|4|1|0|2|0|1|1|1|1|2|2|2|2|1|0|4|2|2|0|1|2|0|1|0|4|0|0|1|2|0|1|1|1|0|2|0|0|1|3|0|2|3|2|0|2|0|1|4|2|1|2|3|1|0|2|1|0|0|0|0|2|1|2|2|0|0|0|1|0|1|1|1|1|1|0|0|1|1|1|0|2|0|0|0|1|1|1|2|0|0|2|0|2|0|2|1|1|0|0|1|2|1|0|1|2|1|2|1|0|2|2|1|0|0|3|0|1|1|1|3|0|1|0|0|0|1|0|1|0|2|3|1|3|2|1|1|0|4|1|0|0|2|3|0|1|0|2|1|1|1|1|0|0|1|2|0|0|0|0|0|1|1|1|0|2|2|0|3|5|0|1|3|2|2|2|4|0|1|3|0|3|0|0|0|1|2|1|2|2|4|1|0|1|3|0|0|0|2|0|1|2|1|2|1|3|1|1|2|0|2|0|1|0|1|1|3|1|2|0|3|0|1|0|1|0|1|0|1|1|1|0|1|1|0|2|0|1|0|1|0|1|1|3|1|0|2|3|0|1|2|0|2|2|1|1|0|0|1|0|2|1|2|0|1|0|1|1|2|0|3|0|2|3|1|2|1|0|3|0|3|0|1|3|0|1|1|0|3|2|1|0|1|1|1|1|0|1|0|1|2|3|3|2|1|1|0|1|1|3|0|1|0|3|2|2|2|2|0|1|1|0|1|2|1|0|1|1|4|2|2|1|2|0|0|0|1|1|0|2|2|0|0|2|0|2|1|0|2|4|0|2|3|1|1|3|0|2|0|1|0|0|0|0|1|3|2|0|1|1|1|0|0|1|2|0|0|0|1|0|0|0|0|1|0|0|1|1|1|1|0|2|1|2|1|0|1|1|0|0|1|0|1|0|0|2|0|0|1|1|1|0|0|2|0|0|1|1|1|0|1|0|3|0|2|1|0|1|2|3|1|1|1|2|0|1|2|0|1|1|0|3|2|1|4|1|2|1|0|0|0|0|1|0|0|1|2|0|1|0|0|1|0|0|0|0|1|1|1|1|2|0|1|1|1|0|2|1|1|1|1|0|1|0|0|2|0|0|1|1|2|0|1|0|3|0|3|0|2|0|2|0|1|1|1|0|0|0|0|0|1|0|1|0|0|2|0|0|2|3|0|0|0|2|1|0|0|1|1|2|1|2|0|0|1|0|1|2|2|0|0|0|3|0|1|2|0|1|3|0|0|0|2|1|1|0|0|1|1|0|1|0|0|1|0|2|0|1|0|0|3|2|0|1|1|0|0|1|0|0|0|1|1|1|0|2|1|1|2|1|2|0|0|1|1|1|1|0|0|1|2|1|0|2|2|0|0|1|1|0|2|0|0|0|0|0|0|0|0|4|0|3|0|0|3|4|0|1|0|0|3|0|2|2|0|0|1|3|2|3|1|0|0|1|0|1|0|2|0|0|0|1|0|0|0|1|0|0|1|1|0|0|2|1|0|1|1|1|0|1|2|0|0|0|1|1|0|1|1|2|1|0|1|1|0|2|0|0|0|2|0|0|1|0|0|1|0|1|1|1|1|0|2|0|0|1|1|1|0|0|1|2|1|0|0|3|2|1|0|0|0|0|1|0|0|1|1|1|0|0|1|1|2|2|0|1|1|0|0|1|2|0|1|2|0|0|0|2|1|2|1|0|0|0|0|1|0|1|1|0|0|2|0|1|1|0|1|2|0|2|1|1|2|0|0|0|0|1|0|2|0|0|1|1|1|2|1|2|1|1|2|2|0|1|0|0|1|0|0|0|2|2|2|2|0|0|1|0|1|1|1|1|1|1|1|1|0|1|1|1|1|0|0|1|0|0|1|0|0|2|0|0|1|2|1|0|0|1|0|0|2|0|0|1|0|0|2|0|0|0|0|3|0|0|1|0|2|1|1|1|0|0|0|0|0|0|1|0|0|0|2|0|2|1|0|1|1|2|0|1|0|2|0|2|2|0|2|0|0|1|0|0|0|3|2|0|1|1|0|2|1|1|1|0|2|0|1|0|1|0|1|0|0|0|1|0|0|1|3|2|1|0|0|0|0|0|0|1|1|0|0|1|0|1|0|0|0|2|1|0|3|1|0|0|0|1|0|0|1|0|0|1|0|0|1|2|0|1|0|1|1|0|0|0|0|0|0|1|0|1|0|1|0|3|0|0|0|0|0|0|2|0|0|1|2|0|1|1|1|0|0|0|0|1|1|0|0|1|2|0|0|0|1|2|2|0|0|0|0|1|1|0|1|1|0|0|1|0|0|0|0|0|0|0|1|1|0|1|2|0|1|3|0|0|1|0|0|0|0|0|0|1|1|0|0|1|0|0|0|3|0|0|0|0|0|0|1|2|1|0|0|0|0|0|0|0|1|0|1|1|1|2|0|0|1|2|1|0|1|1|1|0|0|0|0|2|1|1|0|4|0|0|1|1|1|0|1|0|0|0|0|0|0|0|0|1|0|0|2|0|0|1|1|2|1|0|1|0|1|0|1|1|0|1|0|0|0|2|0|0|0|0|0|0|0|1|0|0|0|1|2|1|1|1|0|0|0|2|0|0|0|0|2|0|0|0|0|1|0|1|0|0|0|0|2|3|0|0|0|0|0|0|1|0|0|0|0|1|2|0|0|0|0|0|0|0|0|0|1|2|0|0|0|0|1|0|0|0|1|0|0|1|0|1|0|0|1|0|1|0|0|0|1|0|1|0|1|0|0|1|0|1|1|1|0|0|0|0|3|1|0|0|0|0|0|1|0|2|2|1|1|0|0|0|2|1|0|0|0|0|0|0|1|0|0|0|0|2|0|0|1|0|0|2|0|1|0|1|1|1|0|0|1|0|0|1|1|0|3|2|0|2|1|0|0|0|0|0|1|0|2|1|0|1|0|0|2|0|0|0|1|0|0|1|0|0|3|0|0|0|0|0|0|1|0|0|2|0|1|2|0|2|0|3|1|0|0|0|1|0|0|0|1|0|0|2|0|1|0|1|1|3|1|1|2|3|0|0|2|0|0|0|0|1|0|0|0|2|0|0|0|1|2|1|1|0|0|0|1|0|1|0|0|0|0|0|2|0|3|0|0|1|0|0|0|0|2|1|0|0|0|2|2|2|1|0|0|1|0|3|0|0|1|1|1|1|0|1|2|0|1|1|0|1|0|1|1|1|0|3|3|4|1|1|0|1|1|0|1|2|2|1|0|0|1|1|1|1|0|2|2|3|0|0|1|2|1|3|1|0|0|0|1|0|1|3|0|2|2|2|0|1|2|1|1|0|1|0|0|1|2|2|0|0|0|0|0|3|0|0|0|1|0|2|1|4|0|0|0|1|2|0|1|2|0|1|1|1|1|2|1|2|0|1|1|0|0|0|0|0|0|0|0|0|2|0|0|2|2|0|3|0|0|0|0|1|0|1|0|1|1|0|0|0|1|1|0|1|0|0|0|0|0|1|2|0|1|1|0|2|0|1|1|0|1|0|0|1|0|0|0|0|0|1|2|0|0|0|0|1|0|0|0|0|0|0|0|0|0|0|0|0|0|0|0|0|0|0|0|0|0|0|0|0|0|0|0|0|0|1|0|0|0|0|0|0|0|0|0|0|0|0|0|1|0|0|0|0|0|0|0|0|0|0|0|0|0|0|0|0|0|0|0|0|0|0|0|0|0|1|0|0|0|0|0|0|0|0|0|0|0|0|0|0|0|0|0|0|0|0|0|0|0|0|0|0|0|0|0|0|0|0|0|0|0|1|0|0|1|0|0|0|0|0|0|0|0|0|0|0|1|0|0|0|1|0|0|0|0|0|0|0|0|0|0|0|1</HistCounts>
      </HistItem>
    </Histograms>
    <Metadata>
      <MDI key="STATISTICS_APPROXIMATE">YES</MDI>
      <MDI key="STATISTICS_MINIMUM">564</MDI>
      <MDI key="STATISTICS_MAXIMUM">6084</MDI>
      <MDI key="STATISTICS_MEAN">1395.7941512598</MDI>
      <MDI key="STATISTICS_STDDEV">683.34728723068</MDI>
      <MDI key="STATISTICS_VALID_PERCENT">6.011</MDI>
    </Metadata>
  </PAMRasterBand>
  <PAMRasterBand band="4">
    <Description>green</Description>
  </PAMRasterBand>
  <PAMRasterBand band="5">
    <Description>yellow</Description>
  </PAMRasterBand>
  <PAMRasterBand band="6">
    <Description>red</Description>
  </PAMRasterBand>
  <PAMRasterBand band="7">
    <Description>rededge</Description>
  </PAMRasterBand>
  <PAMRasterBand band="8">
    <Description>nir</Description>
  </PAMRasterBand>
</PAMDataset>
